fragma/__init__.py
fragma/domain.py
fragma/endchecker.py
fragma/exporter.py
fragma/fragma.py
fragma/models.py
fragma/postprocess.py
fragma/problems.py
fragma/steppers.py
fragma/subproblems.py
fragma/utils/__init__.py
fragma/utils/build_nullspace.py
fragma/utils/parameter_parser.py
fragma/utils/petsc_problems.py
fragma-2026.1.22.dist-info/licenses/LICENSE
fragma-2026.1.22.dist-info/METADATA
fragma-2026.1.22.dist-info/WHEEL
fragma-2026.1.22.dist-info/entry_points.txt
fragma-2026.1.22.dist-info/top_level.txt
fragma-2026.1.22.dist-info/RECORD
