Metadata-Version: 2.4
Name: fragma
Version: 2026.1.22
Summary: A finite element solver, built on top of FEniCSx, for simulating crack propagation using the phase-field approach to fracture.
Author-email: Flavien Loiseau <flavien.loiseau@ensta.fr>
License:                                  Apache License
Project-URL: Documentation, https://floiseau.github.io/fragma/
Project-URL: Source, https://github.com/floiseau/fragma
Classifier: Programming Language :: Python :: 3
Classifier: License :: OSI Approved :: GNU General Public License v3 (GPLv3)
Classifier: Operating System :: OS Independent
License-File: LICENSE
Requires-Dist: numpy
Requires-Dist: sympy
Requires-Dist: scipy
Requires-Dist: pyvista
Dynamic: license-file
